setup.cfg
setup.py
udplogger/__init__.py
udplogger/client.py
udplogger/server.py
udplogger.egg-info/PKG-INFO
udplogger.egg-info/SOURCES.txt
udplogger.egg-info/dependency_links.txt
udplogger.egg-info/requires.txt
udplogger.egg-info/top_level.txt