Metadata-Version: 1.1
Name: udplogger
Version: 2.0.0
Summary: A service for logging messages to a SQL backend via UDP
Home-page: http://github.com/ivotkv/udplogger
Author: Ivo Tzvetkov
Author-email: ivotkv@gmail.com
License: MIT
Download-URL: https://github.com/ivotkv/udplogger/tarball/v2.0.0
Keywords: udp,logger,logging,log
Platform: UNKNOWN
Classifier: Development Status :: 5 - Production/Stable
Classifier: License :: OSI Approved :: MIT License
Classifier: Operating System :: OS Independent
Classifier: Programming Language :: Python :: 2.7
Classifier: Programming Language :: Python :: 3.3
Classifier: Programming Language :: Python :: 3.4
Classifier: Programming Language :: Python :: 3.5
Classifier: Programming Language :: Python :: 3.6
